binary_parser/__init__.py
binary_parser/parser.py
binary_parser-0.0.4.dist-info/LICENSE
binary_parser-0.0.4.dist-info/METADATA
binary_parser-0.0.4.dist-info/WHEEL
binary_parser-0.0.4.dist-info/top_level.txt
binary_parser-0.0.4.dist-info/RECORD
