Metadata-Version: 2.1
Name: binary-parser
Version: 0.0.4
Summary: convert integers to binary and vice-a-versa
Home-page: 
Author: Dhananjay Pai
Author-email: dhananjay2002pai@gmail.com
License: MIT
Keywords: binary to numbers
Platform: UNKNOWN
Classifier: Development Status :: 5 - Production/Stable
Classifier: Intended Audience :: Education
Classifier: Operating System :: Microsoft :: Windows :: Windows 10
Classifier: License :: OSI Approved :: MIT License
Classifier: Programming Language :: Python :: 3
License-File: LICENSE
